github_repo_migrator-0.1.1.dist-info/licenses/LICENSE
repo_migrator/__init__.py
repo_migrator/cli.py
github_repo_migrator-0.1.1.dist-info/METADATA
github_repo_migrator-0.1.1.dist-info/WHEEL
github_repo_migrator-0.1.1.dist-info/entry_points.txt
github_repo_migrator-0.1.1.dist-info/top_level.txt
github_repo_migrator-0.1.1.dist-info/RECORD
