Metadata-Version: 2.4
Name: github-repo-migrator
Version: 0.1.1
Summary: CLI tool to migrate GitHub repos, update global git config and remotes
Author-email: Your Name <you@example.com>
License-File: LICENSE
Dynamic: license-file
